pyskindose/__init__.py
pyskindose/analyze_data.py
pyskindose/beam_class.py
pyskindose/constants.py
pyskindose/corrections.py
pyskindose/db_connect.py
pyskindose/dev_data.py
pyskindose/format_export_data.py
pyskindose/geom_calc.py
pyskindose/main.py
pyskindose/normalization_settings.json
pyskindose/phantom_class.py
pyskindose/rdsr_normalizer.py
pyskindose/rdsr_parser.py
pyskindose/settings_example.json
pyskindose/user_defined_parameters.py
pyskindose/calculate_dose/__init__.py
pyskindose/calculate_dose/add_correction_and_event_dose_to_output.py
pyskindose/calculate_dose/calculate_dose.py
pyskindose/calculate_dose/calculate_irradiation_event_result.py
pyskindose/calculate_dose/perform_calculations_for_new_geometries.py
pyskindose/example_data/RDSR/philips_allura_clarity_u104.dcm
pyskindose/example_data/RDSR/philips_allura_clarity_u601.dcm
pyskindose/example_data/RDSR/siemens_axiom_artis.dcm
pyskindose/example_data/RDSR/siemens_axiom_example_procedure.dcm
pyskindose/helpers/__init__.py
pyskindose/helpers/calculate_rotation_matrices.py
pyskindose/helpers/create_attributes_string.py
pyskindose/helpers/parse_settings_to_settings_class.py
pyskindose/helpers/read_and_normalize_rdsr_data.py
pyskindose/phantom_data/adult_female.stl
pyskindose/phantom_data/adult_female_reduced_1000t.stl
pyskindose/phantom_data/adult_male.stl
pyskindose/phantom_data/adult_male_reduced_1000t.stl
pyskindose/phantom_data/hudfrid.stl
pyskindose/phantom_data/hudfrid_reduced_1000t.stl
pyskindose/phantom_data/junior_female.stl
pyskindose/phantom_data/junior_female_reduced_1000t.stl
pyskindose/phantom_data/junior_male.stl
pyskindose/phantom_data/junior_male_reduced_1000t.stl
pyskindose/phantom_data/senior_female.stl
pyskindose/phantom_data/senior_female_reduced_1000t.stl
pyskindose/phantom_data/senior_male.stl
pyskindose/phantom_data/senior_male_reduced_1000t.stl
pyskindose/plotting/__init__.py
pyskindose/plotting/create_dose_map_plot.py
pyskindose/plotting/create_geometry_plot.py
pyskindose-25.1.1.dist-info/licenses/LICENSE
pyskindose-25.1.1.dist-info/METADATA
pyskindose-25.1.1.dist-info/WHEEL
pyskindose-25.1.1.dist-info/top_level.txt
pyskindose-25.1.1.dist-info/RECORD
