Metadata-Version: 2.4
Name: pyskindose
Version: 25.1.1
Summary: Tools and script for calculating peak skin dose and create dose maps for fluoroscopic exams from RDSR data
Author-email: Max Hellström <max.hellstrom@gmail.com>, Josef Lundman <josef@lundman.eu>
Classifier: Programming Language :: Python :: 3
Classifier: License :: OSI Approved :: MIT License
Classifier: Operating System :: OS Independent
Requires-Python: >=3.10
License-File: LICENSE
Requires-Dist: pandas>=2.2.3
Requires-Dist: numpy>=2.2.4
Requires-Dist: pydicom>=2.0
Requires-Dist: numpy-stl>=3.2.0
Requires-Dist: plotly>=4.13.3
Requires-Dist: scipy>=1.15.2
Requires-Dist: tqdm
Requires-Dist: psutil
Requires-Dist: pillow>=10.0.1
Requires-Dist: kaleido
Requires-Dist: rich
Dynamic: license-file
